{
    "build": {
        "cpu": "cortex-m4",
        "f_cpu": "48000000L",
        "mcu": "AMA3B1KK",
        "part": "apollo3",
        "fabi": "hard",
        "specs": "nano.specs",
        "framework": {
            "arduino": {
                "v1": {
                    "variant": "artemis_dk",
                    "extra_flags": "-DAM_AP3_SFE_ARTEMIS_DK"
                },
                "v2": {
                    "variant": "TARGET_SFE_ARTEMIS_DK",
                    "extra_flags": "-DAPOLLO3_SFE_ARTEMIS_DK"
                }
            },
            "ambiqsdk-sfe": {
                "variant": [
                    "boards_sfe",
                    "artemis_dk"
                ],
                "extra_flags": ""
            }
        }
    },
    "debug": {
        "jlink_device": "AMA3B1KK-KBR",
        "svd_path": "apollo3.svd"
    },
    "frameworks": [
        "arduino",
        "ambiqsdk-sfe"
    ],
    "name": "SparkFun Artemis Development Kit",
    "upload": {
        "maximum_ram_size": 393216,
        "maximum_size": 983040,
        "jlink_offset_address": "0x10000",
        "protocol": "svl",
        "protocols": [
            "svl",
            "asb",
            "jlink"
        ]
    },
    "url": "https://www.sparkfun.com/products/16828",
    "vendor": "SparkFun"
}